{
  "seed": 42,
  "modo_asignacion": "mejora",
  "coordinacion_eje_c": "prioridad_local_movimiento+replaneacion_bloqueo",
  "umbral_replan_bloqueo": 3,
  "replaneaciones_bloqueo": 283,
  "tick_final": 10000,
  "robots": 400,
  "pedidos_totales": 600,
  "pedidos_completados": 591,
  "pedidos_no_completados": 9,
  "tasa_completitud": 0.985,
  "tiempo_promedio_pedido_ticks": 636.269035532995,
  "tiempo_mediana_pedido_ticks": 626.0,
  "tiempo_p90_pedido_ticks": 935.0,
  "tiempo_p95_pedido_ticks": 1032.0,
  "tiempo_std_pedido_ticks": 226.01975799468667,
  "tiempo_min_pedido_ticks": 62.0,
  "tiempo_max_pedido_ticks": 1231.0,
  "throughput_pedidos_por_1000_ticks": 59.1,
  "tiempo_promedio_espera_ticks": 11.9975,
  "tiempo_mediana_espera_ticks": 0.0,
  "tiempo_p90_espera_ticks": 39.0,
  "tiempo_p95_espera_ticks": 51.049999999999955,
  "utilizacion_promedio": 0.09500724999999999,
  "colisiones_vertice": 0,
  "intercambios_arista": 0,
  "deadlock": 0,
  "eventos_alto": 4799,
  "distancia_total_celdas": 374639
}